allwhois/__init__.py
allwhois/_filecache.py
allwhois/normalise.py
allwhois/parser.py
allwhois/query.py
allwhois/version.py
tests/__init__.py
tests/allwhois_tests/__init__.py
tests/allwhois_tests/results.py
tests/allwhois_tests/test_dates.py
tests/allwhois_tests/test_domain_lookups.py
tests/allwhois_tests/test_unicode_domains.py
allwhois-1.0.0.dist-info/LICENSE
allwhois-1.0.0.dist-info/METADATA
allwhois-1.0.0.dist-info/WHEEL
allwhois-1.0.0.dist-info/top_level.txt
allwhois-1.0.0.dist-info/RECORD
