Metadata-Version: 2.1
Name: allwhois
Version: 1.0.0
Summary: Get WHOIS information for a given domain.
Home-page: https://github.com/marirs/allwhois/
Author: Sriram G
Author-email: marirs@gmail.com
License: MIT
Keywords: Python 3,whois,tld,domain,expiration,cctld,domainer,.com,registrar,allwhois,anywhois
Platform: posix
Classifier: Development Status :: 5 - Production/Stable
Classifier: Environment :: Console
Classifier: Intended Audience :: Developers
Classifier: License :: OSI Approved :: MIT License
Classifier: Operating System :: MacOS :: MacOS X
Classifier: Operating System :: POSIX :: Linux
Classifier: Programming Language :: Python :: 3.6
Classifier: Programming Language :: Python :: 3.7
Classifier: Programming Language :: Python :: 3.8
Classifier: Topic :: Internet
Classifier: Topic :: Software Development :: Libraries :: Python Modules
Requires-Python: >=3.6
